{
  "id": "c7f71d55c7c9c54cef8cf89364b2133816480fee",
  "version": 1,
  "className": "io.github.vooft.pepper.sample.ExamplesSpec",
  "name": "multiply by two: example 2",
  "steps": [
    {
      "id": "5ad48eca01494a6fec62e4988c203edf1038c1cd",
      "prefix": "GIVEN",
      "index": 0,
      "name": "multiply 2 by two",
      "status": "PASSED",
      "arguments": [
        {
          "name": "number",
          "type": "kotlin.Int",
          "value": "2"
        }
      ],
      "result": "4",
      "error": null,
      "startedAt": "2024-11-21T19:51:43.002032Z",
      "finishedAt": "2024-11-21T19:51:43.004109Z"
    },
    {
      "id": "2bd00bbc5fbde7cd2318212f33b33d8f3c24e6c5",
      "prefix": "WHEN",
      "index": 1,
      "name": "two ints are compared",
      "status": "PASSED",
      "arguments": [
        {
          "name": "first",
          "type": "kotlin.Int",
          "value": "4"
        },
        {
          "name": "second",
          "type": "kotlin.Int",
          "value": "4"
        }
      ],
      "result": "CompareResult(first=4, second=4, result=true)",
      "error": null,
      "startedAt": "2024-11-21T19:51:43.004331Z",
      "finishedAt": "2024-11-21T19:51:43.006480Z"
    },
    {
      "id": "cad1741ef3a803f805e3be72a50621effb24d3d7",
      "prefix": "THEN",
      "index": 2,
      "name": "compare result is 'true'",
      "status": "PASSED",
      "arguments": [
        {
          "name": "compareResult",
          "type": "io.github.vooft.pepper.sample.CompareResult",
          "value": "CompareResult(first=4, second=4, result=true)"
        },
        {
          "name": "expected",
          "type": "kotlin.Boolean",
          "value": "true"
        }
      ],
      "result": "kotlin.Unit",
      "error": null,
      "startedAt": "2024-11-21T19:51:43.006716Z",
      "finishedAt": "2024-11-21T19:51:43.008802Z"
    }
  ],
  "startedAt": "2024-11-21T19:51:43.001812Z",
  "finishedAt": "2024-11-21T19:51:43.009045Z"
}
