{
  "id": "55c04a2d18a6c32cf5ca2e03942bb51d024ae49f",
  "version": 1,
  "className": "io.github.vooft.pepper.sample.LotOfStepsPepperSpec",
  "name": "my test scenario",
  "steps": [
    {
      "id": "76d176eec509112bbf4826f64722a542a2b4eb92",
      "prefix": "GIVEN",
      "index": 0,
      "name": "generate random string",
      "status": "PASSED",
      "arguments": [
        {
          "name": "prefix",
          "type": "kotlin.String",
          "value": "first"
        }
      ],
      "result": "first 167913730",
      "error": null,
      "startedAt": "2024-11-21T19:50:43.014090Z",
      "finishedAt": "2024-11-21T19:50:43.017160Z"
    },
    {
      "id": "76d176eec509112bbf4826f64722a542a2b4eb92",
      "prefix": "GIVEN",
      "index": 1,
      "name": "generate random string",
      "status": "PASSED",
      "arguments": [
        {
          "name": "prefix",
          "type": "kotlin.String",
          "value": "second"
        }
      ],
      "result": "second -743329333",
      "error": null,
      "startedAt": "2024-11-21T19:50:43.017394Z",
      "finishedAt": "2024-11-21T19:50:43.020451Z"
    },
    {
      "id": "944007ae5d56a056c754860f21efa03075ae0dab",
      "prefix": "WHEN",
      "index": 2,
      "name": "two strings are compared",
      "status": "PASSED",
      "arguments": [
        {
          "name": "first",
          "type": "kotlin.String",
          "value": "first 167913730"
        },
        {
          "name": "second",
          "type": "kotlin.String",
          "value": "second -743329333"
        }
      ],
      "result": "CompareResult(first=first 167913730, second=second -743329333, result=false)",
      "error": null,
      "startedAt": "2024-11-21T19:50:43.020634Z",
      "finishedAt": "2024-11-21T19:50:43.022330Z"
    },
    {
      "id": "f3b27ba8355644ef329dbd7d879320f54d3441c2",
      "prefix": "THEN",
      "index": 3,
      "name": "compare result is 'false'",
      "status": "PASSED",
      "arguments": [
        {
          "name": "compareResult",
          "type": "io.github.vooft.pepper.sample.CompareResult",
          "value": "CompareResult(first=first 167913730, second=second -743329333, result=false)"
        },
        {
          "name": "expected",
          "type": "kotlin.Boolean",
          "value": "false"
        }
      ],
      "result": "kotlin.Unit",
      "error": null,
      "startedAt": "2024-11-21T19:50:43.022527Z",
      "finishedAt": "2024-11-21T19:50:43.024285Z"
    },
    {
      "id": "f3b27ba8355644ef329dbd7d879320f54d3441c2",
      "prefix": "THEN",
      "index": 4,
      "name": "compare result is 'false'",
      "status": "PASSED",
      "arguments": [
        {
          "name": "compareResult",
          "type": "io.github.vooft.pepper.sample.CompareResult",
          "value": "CompareResult(first=first 167913730, second=second -743329333, result=false)"
        },
        {
          "name": "expected",
          "type": "kotlin.Boolean",
          "value": "false"
        }
      ],
      "result": "kotlin.Unit",
      "error": null,
      "startedAt": "2024-11-21T19:50:43.024481Z",
      "finishedAt": "2024-11-21T19:50:43.026350Z"
    },
    {
      "id": "f3b27ba8355644ef329dbd7d879320f54d3441c2",
      "prefix": "THEN",
      "index": 5,
      "name": "compare result is 'false'",
      "status": "PASSED",
      "arguments": [
        {
          "name": "compareResult",
          "type": "io.github.vooft.pepper.sample.CompareResult",
          "value": "CompareResult(first=first 167913730, second=second -743329333, result=false)"
        },
        {
          "name": "expected",
          "type": "kotlin.Boolean",
          "value": "false"
        }
      ],
      "result": "kotlin.Unit",
      "error": null,
      "startedAt": "2024-11-21T19:50:43.026596Z",
      "finishedAt": "2024-11-21T19:50:43.028453Z"
    },
    {
      "id": "f3b27ba8355644ef329dbd7d879320f54d3441c2",
      "prefix": "THEN",
      "index": 6,
      "name": "compare result is 'false'",
      "status": "PASSED",
      "arguments": [
        {
          "name": "compareResult",
          "type": "io.github.vooft.pepper.sample.CompareResult",
          "value": "CompareResult(first=first 167913730, second=second -743329333, result=false)"
        },
        {
          "name": "expected",
          "type": "kotlin.Boolean",
          "value": "false"
        }
      ],
      "result": "kotlin.Unit",
      "error": null,
      "startedAt": "2024-11-21T19:50:43.028699Z",
      "finishedAt": "2024-11-21T19:50:43.030452Z"
    },
    {
      "id": "f3b27ba8355644ef329dbd7d879320f54d3441c2",
      "prefix": "THEN",
      "index": 7,
      "name": "compare result is 'false'",
      "status": "PASSED",
      "arguments": [
        {
          "name": "compareResult",
          "type": "io.github.vooft.pepper.sample.CompareResult",
          "value": "CompareResult(first=first 167913730, second=second -743329333, result=false)"
        },
        {
          "name": "expected",
          "type": "kotlin.Boolean",
          "value": "false"
        }
      ],
      "result": "kotlin.Unit",
      "error": null,
      "startedAt": "2024-11-21T19:50:43.030648Z",
      "finishedAt": "2024-11-21T19:50:43.032402Z"
    },
    {
      "id": "f3b27ba8355644ef329dbd7d879320f54d3441c2",
      "prefix": "THEN",
      "index": 8,
      "name": "compare result is 'false'",
      "status": "PASSED",
      "arguments": [
        {
          "name": "compareResult",
          "type": "io.github.vooft.pepper.sample.CompareResult",
          "value": "CompareResult(first=first 167913730, second=second -743329333, result=false)"
        },
        {
          "name": "expected",
          "type": "kotlin.Boolean",
          "value": "false"
        }
      ],
      "result": "kotlin.Unit",
      "error": null,
      "startedAt": "2024-11-21T19:50:43.032645Z",
      "finishedAt": "2024-11-21T19:50:43.034370Z"
    },
    {
      "id": "f3b27ba8355644ef329dbd7d879320f54d3441c2",
      "prefix": "THEN",
      "index": 9,
      "name": "compare result is 'false'",
      "status": "PASSED",
      "arguments": [
        {
          "name": "compareResult",
          "type": "io.github.vooft.pepper.sample.CompareResult",
          "value": "CompareResult(first=first 167913730, second=second -743329333, result=false)"
        },
        {
          "name": "expected",
          "type": "kotlin.Boolean",
          "value": "false"
        }
      ],
      "result": "kotlin.Unit",
      "error": null,
      "startedAt": "2024-11-21T19:50:43.034599Z",
      "finishedAt": "2024-11-21T19:50:43.036399Z"
    },
    {
      "id": "f3b27ba8355644ef329dbd7d879320f54d3441c2",
      "prefix": "THEN",
      "index": 10,
      "name": "compare result is 'false'",
      "status": "PASSED",
      "arguments": [
        {
          "name": "compareResult",
          "type": "io.github.vooft.pepper.sample.CompareResult",
          "value": "CompareResult(first=first 167913730, second=second -743329333, result=false)"
        },
        {
          "name": "expected",
          "type": "kotlin.Boolean",
          "value": "false"
        }
      ],
      "result": "kotlin.Unit",
      "error": null,
      "startedAt": "2024-11-21T19:50:43.036574Z",
      "finishedAt": "2024-11-21T19:50:43.038337Z"
    },
    {
      "id": "f3b27ba8355644ef329dbd7d879320f54d3441c2",
      "prefix": "THEN",
      "index": 11,
      "name": "compare result is 'false'",
      "status": "PASSED",
      "arguments": [
        {
          "name": "compareResult",
          "type": "io.github.vooft.pepper.sample.CompareResult",
          "value": "CompareResult(first=first 167913730, second=second -743329333, result=false)"
        },
        {
          "name": "expected",
          "type": "kotlin.Boolean",
          "value": "false"
        }
      ],
      "result": "kotlin.Unit",
      "error": null,
      "startedAt": "2024-11-21T19:50:43.038509Z",
      "finishedAt": "2024-11-21T19:50:43.040283Z"
    },
    {
      "id": "f3b27ba8355644ef329dbd7d879320f54d3441c2",
      "prefix": "THEN",
      "index": 12,
      "name": "compare result is 'false'",
      "status": "PASSED",
      "arguments": [
        {
          "name": "compareResult",
          "type": "io.github.vooft.pepper.sample.CompareResult",
          "value": "CompareResult(first=first 167913730, second=second -743329333, result=false)"
        },
        {
          "name": "expected",
          "type": "kotlin.Boolean",
          "value": "false"
        }
      ],
      "result": "kotlin.Unit",
      "error": null,
      "startedAt": "2024-11-21T19:50:43.040466Z",
      "finishedAt": "2024-11-21T19:50:43.042156Z"
    },
    {
      "id": "f3b27ba8355644ef329dbd7d879320f54d3441c2",
      "prefix": "THEN",
      "index": 13,
      "name": "compare result is 'false'",
      "status": "PASSED",
      "arguments": [
        {
          "name": "compareResult",
          "type": "io.github.vooft.pepper.sample.CompareResult",
          "value": "CompareResult(first=first 167913730, second=second -743329333, result=false)"
        },
        {
          "name": "expected",
          "type": "kotlin.Boolean",
          "value": "false"
        }
      ],
      "result": "kotlin.Unit",
      "error": null,
      "startedAt": "2024-11-21T19:50:43.042326Z",
      "finishedAt": "2024-11-21T19:50:43.044006Z"
    },
    {
      "id": "f3b27ba8355644ef329dbd7d879320f54d3441c2",
      "prefix": "THEN",
      "index": 14,
      "name": "compare result is 'false'",
      "status": "PASSED",
      "arguments": [
        {
          "name": "compareResult",
          "type": "io.github.vooft.pepper.sample.CompareResult",
          "value": "CompareResult(first=first 167913730, second=second -743329333, result=false)"
        },
        {
          "name": "expected",
          "type": "kotlin.Boolean",
          "value": "false"
        }
      ],
      "result": "kotlin.Unit",
      "error": null,
      "startedAt": "2024-11-21T19:50:43.044220Z",
      "finishedAt": "2024-11-21T19:50:43.045941Z"
    }
  ],
  "startedAt": "2024-11-21T19:50:43.013927Z",
  "finishedAt": "2024-11-21T19:50:43.046041Z"
}
